sude/__init__.py
sude/clle.py
sude/init_pca.py
sude/learning_l.py
sude/learning_s.py
sude/mds.py
sude/opt_scale.py
sude/pca.py
sude/plotcluster2.py
sude/pps.py
sude-0.1.2.dist-info/METADATA
sude-0.1.2.dist-info/WHEEL
sude-0.1.2.dist-info/RECORD
