Metadata-Version: 2.4
Name: sude
Version: 0.1.2
Summary: A scalable manifold learning (SUDE) method that can cope with large-scale and high-dimensional data in an efficient manner.
Project-URL: Homepage, https://github.com/ZPGuiGroupWhu/SUDE-pkg
Project-URL: Repository, https://github.com/ZPGuiGroupWhu/SUDE-pkg.git
Project-URL: Issues, https://github.com/ZPGuiGroupWhu/SUDE-pkg/issues
Author-email: pdh <pengdh@whu.edu.cn>
License: MIT
Keywords: dimension reduction,embedding,landmark sampling,manifold learning
Classifier: Development Status :: 3 - Alpha
Classifier: Intended Audience :: Science/Research
Classifier: License :: OSI Approved :: MIT License
Classifier: Programming Language :: Python :: 3
Classifier: Programming Language :: Python :: 3.8
Classifier: Programming Language :: Python :: 3.9
Classifier: Programming Language :: Python :: 3.10
Classifier: Programming Language :: Python :: 3.11
Classifier: Topic :: Scientific/Engineering :: Artificial Intelligence
Requires-Python: >=3.8
Requires-Dist: scikit-learn>=1.3.2
